ta/__init__.py
ta/cli.py
ta/core/__init__.py
ta/core/db.py
ta/core/ta.py
ta/core/web_search.py
ta_cli-0.1.1.dist-info/METADATA
ta_cli-0.1.1.dist-info/WHEEL
ta_cli-0.1.1.dist-info/entry_points.txt
ta_cli-0.1.1.dist-info/top_level.txt
ta_cli-0.1.1.dist-info/RECORD
