Metadata-Version: 2.4
Name: ta-cli
Version: 0.1.1
Summary: Add your description here
Requires-Python: >=3.12
Requires-Dist: click>=8.1.8
Requires-Dist: openai>=1.68.1
Requires-Dist: rich>=13.9.4
Requires-Dist: httpx>=0.27.0
Requires-Dist: socksio>=1.0.0
Requires-Dist: playwright>=1.51.0
